silog/__init__.py
silog/silog.py
silog-0.1.3.dist-info/METADATA
silog-0.1.3.dist-info/WHEEL
silog-0.1.3.dist-info/top_level.txt
silog-0.1.3.dist-info/RECORD
