Metadata-Version: 2.1
Name: silog
Version: 0.1.3
Summary: A simple logging library
Home-page: https://github.com/p12m3ikm4d/silog
Author: p12m3ikm4d
Author-email: issue.no9@gmail.com
Classifier: Programming Language :: Python :: 3
Classifier: Operating System :: OS Independent
Requires-Python: >=3.6
